{"isAddBias":true,"inputs":[{"id":0,"x":0.1,"incoming":[]},{"id":1,"x":0.1,"incoming":[]},{"id":2,"x":0.1,"incoming":[]},{"id":3,"x":0.1,"incoming":[]},{"id":4,"x":0.1,"incoming":[]}],"hidden":[],"outputs":[{"id":5,"x":0.9,"incoming":[{"fromId":0,"weight":0.25591627,"enabled":true},{"fromId":1,"weight":1.2987689,"enabled":true},{"fromId":2,"weight":-0.25565967,"enabled":true},{"fromId":3,"weight":-1.093602,"enabled":true},{"fromId":4,"weight":0.09587513,"enabled":true}]},{"id":6,"x":0.9,"incoming":[{"fromId":0,"weight":0.5870377,"enabled":true},{"fromId":1,"weight":-0.055596285,"enabled":true},{"fromId":2,"weight":-0.7964213,"enabled":true},{"fromId":3,"weight":-0.6999539,"enabled":true},{"fromId":4,"weight":-1.21041,"enabled":true}]},{"id":7,"x":0.9,"incoming":[{"fromId":0,"weight":-1.0934255,"enabled":true},{"fromId":1,"weight":0.49887094,"enabled":true},{"fromId":2,"weight":0.0122354925,"enabled":true},{"fromId":3,"weight":0.12678441,"enabled":true},{"fromId":4,"weight":0.97912383,"enabled":true}]},{"id":8,"x":0.9,"incoming":[{"fromId":0,"weight":-0.4198641,"enabled":true},{"fromId":1,"weight":0.77766025,"enabled":true},{"fromId":2,"weight":-1.4917732,"enabled":true},{"fromId":3,"weight":0.8776104,"enabled":true},{"fromId":4,"weight":-1.0861244,"enabled":true}]}]}